Lib_charPk/__init__.py
Lib_charPk/pokemon.csv
Lib_charPk/random_pokemon.py
Lib_charPk-1.0.1.dist-info/METADATA
Lib_charPk-1.0.1.dist-info/WHEEL
Lib_charPk-1.0.1.dist-info/top_level.txt
Lib_charPk-1.0.1.dist-info/RECORD
