Metadata-Version: 2.1
Name: Lib_charPk
Version: 1.0.1
Summary: Es una libreria la cual permitira generar un pokemon  aleatorio
Author: Missael Angel Cardenas 
Author-email: milton_ac@tesch.edu.mx
Requires-Dist: pandas
Requires-Dist: twine
Requires-Dist: wheel
Requires-Dist: setuptools
